kidwai.py
Kidwai-0.1.dist-info/METADATA
Kidwai-0.1.dist-info/WHEEL
Kidwai-0.1.dist-info/top_level.txt
Kidwai-0.1.dist-info/RECORD
